pytraj/version.py
pytraj/all_actions.py
pytraj/io.py
pytraj/__init__.py
pytraj/visualization/__init__.py
pytraj/visualization/view.py
pytraj/topology/__init__.py
pytraj/topology/topology.pxd
pytraj/topology/topology.cpython-37m-darwin.so
pytraj/cluster/__init__.py
pytraj/parallel/__init__.py
pytraj/parallel/dataset.py
pytraj/parallel/mpi.py
pytraj/parallel/multiprocess.py
pytraj/parallel/base.py
pytraj/core/cpp_vector.pxd
pytraj/core/topology_objects.cpython-37m-darwin.so
pytraj/core/c_dict.pxd
pytraj/core/coordinfo.pxd
pytraj/core/box.pxd
pytraj/core/c_core.cpython-37m-darwin.so
pytraj/core/box.cpython-37m-darwin.so
pytraj/core/c_options.cpython-37m-darwin.so
pytraj/core/topology_objects.pxd
pytraj/core/elements.py
pytraj/core/__init__.py
pytraj/core/c_core.pxd
pytraj/core/c_dict.cpython-37m-darwin.so
pytraj/core/coordinfo.cpython-37m-darwin.so
pytraj/core/parameter_types.cpython-37m-darwin.so
pytraj/core/parameter_types.pxd
pytraj/analysis/matrix.py
pytraj/analysis/vector.py
pytraj/analysis/water.py
pytraj/analysis/topology_analysis.py
pytraj/analysis/dihedral_analysis.py
pytraj/analysis/rmsd.py
pytraj/analysis/nmr.py
pytraj/analysis/__init__.py
pytraj/analysis/dssp_analysis.py
pytraj/analysis/energy_analysis.py
pytraj/analysis/nucleic_acid_analysis.py
pytraj/analysis/hbond_analysis.py
pytraj/analysis/base_holder.py
pytraj/analysis/c_analysis/c_analysis.pxd
pytraj/analysis/c_analysis/__init__.py
pytraj/analysis/c_analysis/c_analysis.cpython-37m-darwin.so
pytraj/analysis/c_analysis/analysis_dict.py
pytraj/analysis/c_action/c_action.cpython-37m-darwin.so
pytraj/analysis/c_action/actionlist.cpython-37m-darwin.so
pytraj/analysis/c_action/__init__.py
pytraj/analysis/c_action/actionlist.pxd
pytraj/analysis/c_action/c_action.pxd
pytraj/datasets/c_datasets.cpython-37m-darwin.so
pytraj/datasets/c_datasetlist.cpython-37m-darwin.so
pytraj/datasets/cast_dataset.cpython-37m-darwin.so
pytraj/datasets/c_datasets.pxd
pytraj-2.0.5.dist-info/RECORD
pytraj-2.0.5.dist-info/WHEEL
pytraj-2.0.5.dist-info/top_level.txt
pytraj-2.0.5.dist-info/METADATA
